karabo_sls_detectors/bin/karabo-sls-detector-server
karabo_sls_detectors/shims/entrypoints.py
karabo_sls_detectors/slsDetectors/libslsDetectors.so
karabo_sls_detectors.libs/libSlsDetector-ddb316a3.so.9.2.0
karabo_sls_detectors.libs/libSlsReceiver-9d239c86.so.9.2.0
karabo_sls_detectors.libs/libamqpcpp-af17cbf9.so.4.3
karabo_sls_detectors.libs/libboost_atomic-306ed786.so.1.88.0
karabo_sls_detectors.libs/libboost_chrono-bdd922c8.so.1.88.0
karabo_sls_detectors.libs/libboost_container-ada431f4.so.1.88.0
karabo_sls_detectors.libs/libboost_date_time-5de398e8.so.1.88.0
karabo_sls_detectors.libs/libboost_regex-0485f5e1.so.1.88.0
karabo_sls_detectors.libs/libboost_system-51075d83.so.1.88.0
karabo_sls_detectors.libs/libboost_thread-38335b7b.so.1.88.0
karabo_sls_detectors.libs/libcrypto-6e2f857a.so.1.1
karabo_sls_detectors.libs/libcurl-914f668e.so.4
karabo_sls_detectors.libs/libdate-tz-f2e80ffa.so.3
karabo_sls_detectors.libs/libfmt-c961d355.so.10
karabo_sls_detectors.libs/libkarabo-3d803d81.so.3
karabo_sls_detectors.libs/libpugixml-3b16ec94.so.1
karabo_sls_detectors.libs/libslsDetectors-c0d8c66d.so
karabo_sls_detectors.libs/libspdlog-21d6b95b.so.1.14
karabo_sls_detectors.libs/libssl-62e44dcb.so.1.1
karabo_sls_detectors-3.0.4.dist-info/METADATA
karabo_sls_detectors-3.0.4.dist-info/WHEEL
karabo_sls_detectors-3.0.4.dist-info/entry_points.txt
karabo_sls_detectors-3.0.4.dist-info/RECORD
karabo_sls_detectors-3.0.4.dist-info/licenses/LICENSE.md
